MANIFEST.in
setup.py
bin/geotweet
geotweet/__init__.py
geotweet/osm.py
geotweet.egg-info/PKG-INFO
geotweet.egg-info/SOURCES.txt
geotweet.egg-info/dependency_links.txt
geotweet.egg-info/requires.txt
geotweet.egg-info/top_level.txt
geotweet/data/stopwords.txt
geotweet/geomongo/__init__.py
geotweet/geomongo/load.py
geotweet/geomongo/mongo.py
geotweet/mapreduce/__init__.py
geotweet/mapreduce/metro_wordcount.py
geotweet/mapreduce/poi_nearby_tweets.py
geotweet/mapreduce/state_county_wordcount.py
geotweet/mapreduce/utils/__init__.py
geotweet/mapreduce/utils/lookup.py
geotweet/mapreduce/utils/proj.py
geotweet/mapreduce/utils/reader.py
geotweet/mapreduce/utils/words.py
geotweet/twitter/__init__.py
geotweet/twitter/geotweet.py
geotweet/twitter/load.py
geotweet/twitter/stream.py
geotweet/twitter/stream_steps.py