Metadata-Version: 1.0
Name: geotweet
Version: 0.2.7
Summary: Fetch geographic tweets from Twitter Streaming API
Home-page: https://github.com/meyersj/geotweet
Author: Jeffrey Alan Meyers
Author-email: jeffrey.alan.meyers@gmail.com
License: UNKNOWN
Platform: UNKNOWN
